gumpython/__init__.py
gumpython/__version__.py
gumpython/arguments/__init__.py
gumpython/arguments/arguments.py
gumpython/commands/__init__.py
gumpython/commands/choose.py
gumpython/commands/command.py
gumpython/commands/confirm.py
gumpython/commands/filter.py
gumpython/commands/format.py
gumpython/commands/input.py
gumpython/commands/join.py
gumpython/commands/spin.py
gumpython/commands/style.py
gumpython/commands/write.py
gumpython/constants.py
gumpython/exceptions.py
gumpython/flags/__init__.py
gumpython/flags/choose_flags.py
gumpython/flags/confirm_flags.py
gumpython/flags/filter_flags.py
gumpython/flags/flags.py
gumpython/flags/format_flags.py
gumpython/flags/input_flags.py
gumpython/flags/join_flags.py
gumpython/flags/spin_flags.py
gumpython/flags/style_flags.py
gumpython/flags/write_flags.py
gumpython/inputs/__init__.py
gumpython/inputs/alignment.py
gumpython/inputs/basic.py
gumpython/inputs/border.py
gumpython/inputs/color.py
gumpython/inputs/format.py
gumpython/inputs/help_inputs/__init__.py
gumpython/inputs/help_inputs/alignment_types.py
gumpython/inputs/help_inputs/border_types.py
gumpython/inputs/help_inputs/color_names.py
gumpython/inputs/help_inputs/format_types.py
gumpython/inputs/help_inputs/spinner_types.py
gumpython/inputs/inputs.py
gumpython/inputs/position.py
gumpython/inputs/spinner.py
gumpython/run_command.py
gumpython/style.py
gumpython/utils.py
gumpython-0.3.0.dist-info/LICENSE
gumpython-0.3.0.dist-info/WHEEL
gumpython-0.3.0.dist-info/METADATA
gumpython-0.3.0.dist-info/RECORD
